LICENSE.txt
MANIFEST.in
README.md
requirements.txt
setup.py
idx2numpy/FormatError.py
idx2numpy/__init__.py
idx2numpy/converters.py
idx2numpy/version.py
idx2numpy.egg-info/PKG-INFO
idx2numpy.egg-info/SOURCES.txt
idx2numpy.egg-info/dependency_links.txt
idx2numpy.egg-info/not-zip-safe
idx2numpy.egg-info/requires.txt
idx2numpy.egg-info/top_level.txt
idx2numpy/test/__init__.py
idx2numpy/test/converters_test.py
idx2numpy/test/files/correct.idx
idx2numpy/test/files/empty.idx